test2_ljovan_vihaus_pkg/__init__.py
test2_ljovan_vihaus_pkg/cli.py
test2_ljovan_vihaus_pkg/test_tweet_preprocessor.py
test2_ljovan_vihaus_pkg/tweet_preprocessor.py
test2_ljovan_vihaus-0.0.1.dist-info/LICENSE
test2_ljovan_vihaus-0.0.1.dist-info/METADATA
test2_ljovan_vihaus-0.0.1.dist-info/WHEEL
test2_ljovan_vihaus-0.0.1.dist-info/entry_points.txt
test2_ljovan_vihaus-0.0.1.dist-info/top_level.txt
test2_ljovan_vihaus-0.0.1.dist-info/RECORD
