Metadata-Version: 2.1
Name: test2-ljovan-vihaus
Version: 0.0.1
Summary: test of vihaus_ljovan_pckg
Home-page: https://github.com/pypa/sampleproject
Author: vihaus & ljovan
Author-email: stercus.cursus@pm.me
License: UNKNOWN
Platform: UNKNOWN
Classifier: Programming Language :: Python :: 3
Classifier: License :: OSI Approved :: MIT License
Classifier: Operating System :: OS Independent
Requires-Python: >=3.6
Requires-Dist: emoji
Requires-Dist: nltk
